bundlepy/__init__.py
bundlepy/bundle_service/__init__.py
bundlepy/bundle_service/bundle_service.py
bundlepy/bundle_service/hidden_imports_bundler_service.txt
bundlepy/bundle_service/packages_bundler_service.txt
bundlepy/bundler.py
bundlepy/bundler_arguments.py
bundlepy/config/cluster_conf.json
bundlepy/main.py
bundlepy/remote_bundler.py
bundlepy/venv_manager.py
bundlepy-0.2.0.dist-info/LICENSE
bundlepy-0.2.0.dist-info/METADATA
bundlepy-0.2.0.dist-info/WHEEL
bundlepy-0.2.0.dist-info/entry_points.txt
bundlepy-0.2.0.dist-info/RECORD
